odoo/addons/odoo_project_stat/README.rst
odoo/addons/odoo_project_stat/__init__.py
odoo/addons/odoo_project_stat/__manifest__.py
odoo/addons/odoo_project_stat/data/odoo_project_stat_config.xml
odoo/addons/odoo_project_stat/models/__init__.py
odoo/addons/odoo_project_stat/models/odoo_project.py
odoo/addons/odoo_project_stat/models/odoo_project_stat.py
odoo/addons/odoo_project_stat/models/odoo_project_stat_config.py
odoo/addons/odoo_project_stat/readme/CONTRIBUTORS.md
odoo/addons/odoo_project_stat/readme/DESCRIPTION.md
odoo/addons/odoo_project_stat/security/ir.model.access.csv
odoo/addons/odoo_project_stat/static/description/icon.png
odoo/addons/odoo_project_stat/static/description/index.html
odoo/addons/odoo_project_stat/static/img/project_pie_charts.png
odoo/addons/odoo_project_stat/views/odoo_project.xml
odoo/addons/odoo_project_stat/views/odoo_project_stat_config.xml
odoo/addons/odoo_project_stat/wizards/__init__.py
odoo/addons/odoo_project_stat/wizards/odoo_project_import_modules.py
odoo_addon_odoo_project_stat-16.0.1.0.1.dist-info/METADATA
odoo_addon_odoo_project_stat-16.0.1.0.1.dist-info/WHEEL
odoo_addon_odoo_project_stat-16.0.1.0.1.dist-info/top_level.txt
odoo_addon_odoo_project_stat-16.0.1.0.1.dist-info/RECORD
